diff_viewer/__init__.py
diff_viewer/frontend/build/asset-manifest.json
diff_viewer/frontend/build/bootstrap.min.css
diff_viewer/frontend/build/index.html
diff_viewer/frontend/build/precache-manifest.d71c6050632541dc38ffc343d72bb0ed.js
diff_viewer/frontend/build/prism.css
diff_viewer/frontend/build/prism.js
diff_viewer/frontend/build/service-worker.js
diff_viewer/frontend/build/static/js/2.d9e47561.chunk.js
diff_viewer/frontend/build/static/js/2.d9e47561.chunk.js.LICENSE.txt
diff_viewer/frontend/build/static/js/2.d9e47561.chunk.js.map
diff_viewer/frontend/build/static/js/main.d8ab51cc.chunk.js
diff_viewer/frontend/build/static/js/main.d8ab51cc.chunk.js.map
diff_viewer/frontend/build/static/js/runtime-main.11ec9aca.js
diff_viewer/frontend/build/static/js/runtime-main.11ec9aca.js.map
streamlit_diff_viewer-0.0.2.dist-info/LICENSE
streamlit_diff_viewer-0.0.2.dist-info/METADATA
streamlit_diff_viewer-0.0.2.dist-info/WHEEL
streamlit_diff_viewer-0.0.2.dist-info/top_level.txt
streamlit_diff_viewer-0.0.2.dist-info/RECORD
