Metadata-Version: 2.1
Name: streamlit-diff-viewer
Version: 0.0.2
Summary: A simple component to view diff between to files
Home-page: UNKNOWN
Author: Quentin Febvre
Author-email: quentin.febvre@gmail.com
License: UNKNOWN
Platform: UNKNOWN
Requires-Python: >=3.6
Requires-Dist: streamlit (>=0.63)
